dash_arcgis_open/BaseMapGallery.py
dash_arcgis_open/BasemapGallery.py
dash_arcgis_open/Bookmarks.py
dash_arcgis_open/Editor.py
dash_arcgis_open/Expand.py
dash_arcgis_open/GeoJSONLayer.py
dash_arcgis_open/MapView.py
dash_arcgis_open/WebMap.py
dash_arcgis_open/_imports_.py
dash_arcgis_open/dash_arcgis_open.min.js
dash_arcgis_open/dash_arcgis_open.min.js.map
dash_arcgis_open/metadata.json
dash_arcgis_open/package-info.json
dash_arcgis_open-0.0.3.dist-info/LICENSE
dash_arcgis_open-0.0.3.dist-info/METADATA
dash_arcgis_open-0.0.3.dist-info/WHEEL
dash_arcgis_open-0.0.3.dist-info/top_level.txt
dash_arcgis_open-0.0.3.dist-info/RECORD
