Metadata-Version: 2.1
Name: dash-arcgis-open
Version: 0.0.3
Summary: Open Source implementation of Plotly Dash mapping components, powered by the ESRI ArcGIS API for Javascript.
Author: James Holcombe  <jholcombe@hotmail.co.uk>
License: MIT
Keywords: Dash,Plotly,ESRI,ArcGIS,Map,Mapping
Classifier: Framework :: Dash
License-File: LICENSE
